spacy_cymraeg/__init__.py
spacy_cymraeg/lemmatizer.py
spacy_cymraeg/lex_attrs.py
spacy_cymraeg/punctuation.py
spacy_cymraeg/stop_words.py
spacy_cymraeg/tokenizer_exceptions.py
spacy_cymraeg-0.1.1.dist-info/METADATA
spacy_cymraeg-0.1.1.dist-info/WHEEL
spacy_cymraeg-0.1.1.dist-info/RECORD
