Metadata-Version: 2.4
Name: spacy-cymraeg
Version: 0.1.1
Summary: An installable version of Techiaith's cy model for SpaCy
Project-URL: homepage, https://gitlab.com/prvInSpace/spacy-cymraeg
Project-URL: repository, https://gitlab.com/prvInSpace/spacy-cymraeg
Author-email: Preben Vangberg <prv21fgt@bangor.ac.uk>
License-Expression: MIT
Requires-Python: >=3.9
Requires-Dist: spacy>=3.5
